PyNL-2020.0.1.data/data/imsl/LICENSE
PyNL-2020.0.1.data/data/imsl/NOTICE.rst
imsl/__init__.py
imsl/_constants.py
imsl/_imsllib.py
imsl/_structures.py
imsl/constants.py
imsl/error.py
imsl/version.py
imsl/cluster/__init__.py
imsl/cluster/cluster_k_means.py
imsl/data_mining/__init__.py
imsl/data_mining/apriori.py
imsl/data_mining/decision_tree.py
imsl/eigen/__init__.py
imsl/eigen/eig_gen.py
imsl/linalg/__init__.py
imsl/linalg/lin_lsq_lin_constraints.py
imsl/linalg/lu.py
imsl/optimize/__init__.py
imsl/optimize/sparse_lp.py
imsl/regression/__init__.py
imsl/regression/logistic_regression.py
imsl/regression/pls_regression.py
imsl/timeseries/__init__.py
imsl/timeseries/auto_arima.py
imsl/timeseries/garch.py
PyNL-2020.0.1.dist-info/LICENSE
PyNL-2020.0.1.dist-info/METADATA
PyNL-2020.0.1.dist-info/NOTICE.rst
PyNL-2020.0.1.dist-info/WHEEL
PyNL-2020.0.1.dist-info/top_level.txt
PyNL-2020.0.1.dist-info/zip-safe
PyNL-2020.0.1.dist-info/RECORD
