Metadata-Version: 2.1
Name: PyNL
Version: 2020.0.1
Summary: IMSL Library for Python
Home-page: https://www.imsl.com/products/imsl-python-libraries
Author: Rogue Wave Software, Inc.
Author-email: support@roguewave.com
Maintainer: Rogue Wave Software, Inc.
Maintainer-email: support@roguewave.com
License: UNKNOWN
Platform: UNKNOWN
Classifier: Development Status :: 5 - Production/Stable
Classifier: Intended Audience :: Developers
Classifier: Intended Audience :: Education
Classifier: Intended Audience :: End Users/Desktop
Classifier: Intended Audience :: Science/Research
Classifier: License :: OSI Approved :: Apache Software License
Classifier: Operating System :: Microsoft :: Windows
Classifier: Operating System :: POSIX :: Linux
Classifier: Programming Language :: Python
Classifier: Programming Language :: Python :: 2.7
Classifier: Programming Language :: Python :: 3.5
Classifier: Programming Language :: Python :: 3.6
Classifier: Programming Language :: Python :: 3.7
Classifier: Programming Language :: Python :: 3.8
Classifier: Programming Language :: Python :: Implementation :: CPython
Classifier: Topic :: Scientific/Engineering
Classifier: Topic :: Software Development
Requires-Dist: numpy (>=1.16.5)
Requires-Dist: scipy (>=1.2.2)
